idem_cloud/conf.py
idem_cloud/scripts.py
idem_cloud/version.py
idem_cloud/src/init.py
idem_cloud-1.0.1.dist-info/LICENSE
idem_cloud-1.0.1.dist-info/METADATA
idem_cloud-1.0.1.dist-info/WHEEL
idem_cloud-1.0.1.dist-info/top_level.txt
idem_cloud-1.0.1.dist-info/RECORD
