Metadata-Version: 2.1
Name: idem-cloud
Version: 1.0.1
Summary: Meta package for idem-cloud resources
Home-page: https://gitlab.com/saltstack/pop/idem-cloud
Author: Tyler Johnson
Author-email: tyjohnson@vmware.com
License: UNKNOWN
Platform: UNKNOWN
Classifier: Environment :: Console
Classifier: Intended Audience :: Developers
Classifier: Intended Audience :: Information Technology
Classifier: Intended Audience :: System Administrators
Classifier: Operating System :: OS Independent
Classifier: Programming Language :: Python
Classifier: Programming Language :: Python :: 3.6
Classifier: Programming Language :: Python :: 3.7
Classifier: Programming Language :: Python :: 3.8
Classifier: Programming Language :: Python :: 3.9
Classifier: Development Status :: 5 - Production/Stable
Requires-Python: >=3.6
License-File: LICENSE
Requires-Dist: pop (>=20.0.0)
Requires-Dist: idem (>=13.0.1)
Requires-Dist: idem-aiohttp
Requires-Dist: idem-aws
Provides-Extra: full
